{
  "Documents": {
    "167988": {
      "backImage": "https://firebasestorage.googleapis.com/v0/b/whale-profits.appspot.com/o/Document_image%2F1696524859407_0.jpeg?alt=media&token=7b900e25-6ba2-4441-9e42-f557baaa505c",
      "frontImage": "https://firebasestorage.googleapis.com/v0/b/whale-profits.appspot.com/o/Document_image%2F1696524850097_0.jpeg?alt=media&token=29fbe08e-75f8-4ce2-89fa-24e5be3d7383",
      "verified": true
    },
    "484805": {
      "backImage": "https://firebasestorage.googleapis.com/v0/b/whale-profits.appspot.com/o/Document_image%2F1696527467795_0.png?alt=media&token=dc37fd33-7ff6-43cd-879c-a8dbc9bb77fc",
      "frontImage": "https://firebasestorage.googleapis.com/v0/b/whale-profits.appspot.com/o/Document_image%2F1696527460512_0.png?alt=media&token=07260140-0cf1-46e3-9dd1-7b4cd61ad9fc",
      "verified": true
    },
    "558107": {
      "backImage": "https://firebasestorage.googleapis.com/v0/b/whale-profits.appspot.com/o/Document_image%2F1696355236270_0.jpeg?alt=media&token=dd0f3815-192a-4d34-bf91-571032d124ca",
      "frontImage": "https://firebasestorage.googleapis.com/v0/b/whale-profits.appspot.com/o/Document_image%2F1696355227168_0.jpeg?alt=media&token=09b473af-408a-47c1-87a4-c6510e22605e",
      "verified": true
    },
    "665416": {
      "backImage": "https://firebasestorage.googleapis.com/v0/b/whale-profits.appspot.com/o/Document_image%2F1696525996730_0.png?alt=media&token=b27a118b-55c9-4db5-8d87-6e53eed8c6b5",
      "frontImage": "https://firebasestorage.googleapis.com/v0/b/whale-profits.appspot.com/o/Document_image%2F1696525985613_0.png?alt=media&token=c2a19c3a-7ccc-48af-b195-8c92c307160d",
      "verified": true
    },
    "719240": {
      "backImage": "https://firebasestorage.googleapis.com/v0/b/whale-profits.appspot.com/o/Document_image%2F1696526936334_0.png?alt=media&token=2d825ab1-5d6f-41fb-bf7b-3d7c97678b89",
      "frontImage": "https://firebasestorage.googleapis.com/v0/b/whale-profits.appspot.com/o/Document_image%2F1696526927616_0.png?alt=media&token=9a94ace9-c4ce-4bce-92e3-5a41b999d161",
      "verified": true
    },
    "767740": {
      "backImage": "https://firebasestorage.googleapis.com/v0/b/whale-profits.appspot.com/o/Document_image%2F1696178099397_0.jpeg?alt=media&token=ec8a22e3-4011-42ce-a23b-7add7414a931",
      "frontImage": "https://firebasestorage.googleapis.com/v0/b/whale-profits.appspot.com/o/Document_image%2F1696178069562_0.jpeg?alt=media&token=0ab5e2e0-f905-4b96-a542-f0189394c820",
      "verified": true
    },
    "793175": {
      "backImage": "https://firebasestorage.googleapis.com/v0/b/whale-profits.appspot.com/o/Document_image%2F1696515338789_0.jpg?alt=media&token=3a3a519c-7d33-4e69-ad2f-442c20cd89d9",
      "frontImage": "https://firebasestorage.googleapis.com/v0/b/whale-profits.appspot.com/o/Document_image%2F1696515330752_0.jpg?alt=media&token=60b1a6a3-093b-4d94-9c52-1316ac738f68",
      "verified": true
    },
    "991612": {
      "backImage": "https://firebasestorage.googleapis.com/v0/b/whale-profits.appspot.com/o/Document_image%2F1696527393071_0.png?alt=media&token=a00923aa-0a37-4343-bfda-8bb94d5ebbe5",
      "frontImage": "https://firebasestorage.googleapis.com/v0/b/whale-profits.appspot.com/o/Document_image%2F1696527383003_0.png?alt=media&token=6bf0981f-7fd9-4a51-a514-636de5a4fdb7",
      "verified": true
    },
    "998324": {
      "backImage": "https://firebasestorage.googleapis.com/v0/b/whale-profits.appspot.com/o/Document_image%2F1696526784682_0.png?alt=media&token=bdfa44ae-750e-4d76-8a52-6a7b7f46154c",
      "frontImage": "https://firebasestorage.googleapis.com/v0/b/whale-profits.appspot.com/o/Document_image%2F1696526775852_0.png?alt=media&token=edafcdfa-7745-432b-acc5-3e439bf81898",
      "verified": true
    },
    "095846": {
      "backImage": "https://firebasestorage.googleapis.com/v0/b/whale-profits.appspot.com/o/Document_image%2F1696527102761_0.png?alt=media&token=9ac524ad-e00b-4330-ac98-251a652754ca",
      "frontImage": "https://firebasestorage.googleapis.com/v0/b/whale-profits.appspot.com/o/Document_image%2F1696527080546_0.png?alt=media&token=fb41d0a7-ce69-4855-9835-2070beb59da2",
      "verified": true
    }
  },
  "aboutus": "sdafljk aidsfj isdf aiosf oaisjfd  sojfa sodjf so ef ",
  "addresses": {
    "USDT(BEP-20)": {
      "wallet": "test address"
    },
    "USDT(TRC-20)": {
      "wallet": "test trx address"
    },
    "lastUpdateDate": "2023-09-30T11:47:56.535Z"
  },
  "completedContracts": {
    "793175": {
      "balance": 100,
      "date": "2023-10-05T16:03:41.499Z",
      "earned": 3000,
      "level": 3,
      "plan": 600
    }
  },
  "courses": {
    "-Ng-mc2DWjJQorwdrLk0": {
      "id": "-Ng-mc2DWjJQorwdrLk0",
      "links": [
        null,
        {
          "link": "link test 2",
          "title": "Day 2"
        },
        {
          "link": "test 3",
          "title": "link 3"
        }
      ],
      "title": "Learning Investements Course"
    },
    "-Ng0WvN5a5VM-PMbfEbM": {
      "id": "-Ng0WvN5a5VM-PMbfEbM",
      "links": [
        {
          "link": "link test",
          "title": "Link test"
        }
      ],
      "title": "Course 2"
    }
  },
  "learning": {
    "-NflTg6OQz71ethTyz-c": {
      "link": "https://www.youtube.com/watch?v=K1N7PB72ecA&ab_channel=AMTEE",
      "title": "This video contains learning about investment"
    },
    "-NflU0iRYV8kH075opde": {
      "link": "gfdh",
      "title": "rtdyd"
    },
    "-NfqgCTnuivnKZjbEb2j": {
      "link": "sdafasdfdf",
      "title": "asfasdf"
    }
  },
  "oneTimeRefferalPayment": {
    "percentage": 10
  },
  "plans": [
    null,
    null,
    {
      "amount": "400",
      "level": "2",
      "potentialEarning": "2000"
    },
    {
      "amount": "600",
      "level": "3",
      "potentialEarning": "3000"
    },
    {
      "amount": "800",
      "level": "4",
      "potentialEarning": "4000"
    },
    {
      "amount": "1000",
      "level": "5",
      "potentialEarning": "5000"
    },
    {
      "amount": "1500",
      "level": "6",
      "potentialEarning": "7500"
    },
    {
      "amount": "2000",
      "level": "7",
      "potentialEarning": "10000"
    }
  ],
  "popupConfig": {
    "imageUrl": "https://firebasestorage.googleapis.com/v0/b/whale-profits.appspot.com/o/PopUp_image.jpg?alt=media&token=d8c16e5f-21b0-4e94-83c7-d4524b81f7e4",
    "isEnabled": true,
    "text": "This is the watch you should buy beacause it is a very expensice and good watch and you will look handsome in wearing that watch"
  },
  "privacypolicy": "jhfsdauhfaisodfh oasodifj awief saidf asidf ewif slkdafj aieufj asdifj aoiefj sioeuf asodjfawoi eur fasofa soifu aeiru aoewirjawoiefuaoieu fawieruao sidu oweu roiaje ur eoiwuriowe or aowuer oiwuer iauwefaoshfi ei rw aruoiw a ewiuroai  aeoiu ",
  "requests": {
    "-Ng-BnWO6Uj6DBDf0yU9": {
      "amount": "600",
      "chain": "bnb",
      "id": "qtKGMZesb1OkLhNMIB6oYSBChxq2",
      "level": "3",
      "referredBy": "767740",
      "request": "Deposit",
      "requestId": "-Ng-BnWO6Uj6DBDf0yU9",
      "status": "Completed",
      "timestamp": 1696515438906,
      "trxId": "Test id",
      "username": "793175"
    },
    "-Ng-DzBhelBgPnVXYVaU": {
      "amount": "800",
      "chain": "bnb",
      "id": "qtKGMZesb1OkLhNMIB6oYSBChxq2",
      "level": "4",
      "referredBy": "767740",
      "request": "Deposit",
      "requestId": "-Ng-DzBhelBgPnVXYVaU",
      "status": "Completed",
      "timestamp": 1696516011019,
      "trxId": "Dff",
      "username": "793175"
    },
    "-Ng-YSCv63deqRsxIZNo": {
      "amount": "400",
      "chain": "USDT(BEP-20)",
      "id": "qtKGMZesb1OkLhNMIB6oYSBChxq2",
      "level": "2",
      "referredBy": "767740",
      "request": "Deposit",
      "requestId": "-Ng-YSCv63deqRsxIZNo",
      "status": "Completed",
      "timestamp": 1696521376377,
      "trxId": "id",
      "username": "793175"
    },
    "-Ng-ZJz_quDlXQeQMKHk": {
      "amount": "600",
      "chain": "USDT(BEP-20)",
      "id": "qtKGMZesb1OkLhNMIB6oYSBChxq2",
      "level": "3",
      "referredBy": "767740",
      "request": "Deposit",
      "requestId": "-Ng-ZJz_quDlXQeQMKHk",
      "status": "Completed",
      "timestamp": 1696521604815,
      "trxId": "sda",
      "username": "793175"
    },
    "-Ng-Zj5wIGCs4o5jd9S8": {
      "amount": "600",
      "chain": "USDT(BEP-20)",
      "id": "qtKGMZesb1OkLhNMIB6oYSBChxq2",
      "level": "3",
      "referredBy": "767740",
      "request": "Deposit",
      "requestId": "-Ng-Zj5wIGCs4o5jd9S8",
      "status": "Completed",
      "timestamp": 1696521711779,
      "trxId": "asddas",
      "username": "793175"
    },
    "-Ng-_uLqqc0hfjufMplh": {
      "amount": "600",
      "chain": "USDT(BEP-20)",
      "id": "qtKGMZesb1OkLhNMIB6oYSBChxq2",
      "level": "3",
      "referredBy": "767740",
      "request": "Deposit",
      "requestId": "-Ng-_uLqqc0hfjufMplh",
      "status": "Completed",
      "timestamp": 1696522019997,
      "trxId": "asd",
      "username": "793175"
    },
    "-Ng-pafJLPJxhSuQnYH9": {
      "amount": "600",
      "chain": "USDT(BEP-20)",
      "id": "DQqP1eorEBf8n48PBWAQYxRfQoS2",
      "level": "3",
      "referredBy": "793175",
      "request": "Deposit",
      "requestId": "-Ng-pafJLPJxhSuQnYH9",
      "status": "Completed",
      "timestamp": 1696526133631,
      "trxId": "sdf",
      "username": "665416"
    },
    "-Ng-qH7IH0CbCh_Id56F": {
      "amount": "600",
      "chain": "USDT(BEP-20)",
      "id": "DQqP1eorEBf8n48PBWAQYxRfQoS2",
      "level": "3",
      "referredBy": "793175",
      "request": "Deposit",
      "requestId": "-Ng-qH7IH0CbCh_Id56F",
      "status": "Completed",
      "timestamp": 1696526311611,
      "trxId": "sdfa",
      "username": "665416"
    },
    "-Ng-v3xFBLrTotgPaUHj": {
      "amount": "200",
      "chain": "USDT(BEP-20)",
      "id": "hAAFczQnMtOvyywM6g2T4eqEvDD3",
      "level": "1",
      "referredBy": "793175",
      "request": "Deposit",
      "requestId": "-Ng-v3xFBLrTotgPaUHj",
      "status": "Completed",
      "timestamp": 1696527568385,
      "trxId": "sad",
      "username": "998324"
    },
    "-Ng-vFbU3q7mMhJhRkUc": {
      "amount": "400",
      "chain": "USDT(BEP-20)",
      "id": "qCz196NhHST7HNZ6wVgZa1Lqvfn1",
      "level": "2",
      "referredBy": "793175",
      "request": "Deposit",
      "requestId": "-Ng-vFbU3q7mMhJhRkUc",
      "status": "Completed",
      "timestamp": 1696527616182,
      "trxId": "dfs",
      "username": "095846"
    },
    "-Ng-vTKeMiBm0bR_CLFW": {
      "amount": "600",
      "chain": "USDT(BEP-20)",
      "id": "B34ZB29qiZQTPTmCgkqaofyGppn1",
      "level": "3",
      "referredBy": "793175",
      "request": "Deposit",
      "requestId": "-Ng-vTKeMiBm0bR_CLFW",
      "status": "Completed",
      "timestamp": 1696527672326,
      "trxId": "dsfsg",
      "username": "719240"
    },
    "-Ng-w2Rcw7uU37dyq4IK": {
      "amount": "1500",
      "chain": "USDT(BEP-20)",
      "id": "u8Mdv9xvD4bW8bEUfchLoN0ucn22",
      "level": "6",
      "referredBy": "793175",
      "request": "Deposit",
      "requestId": "-Ng-w2Rcw7uU37dyq4IK",
      "status": "Completed",
      "timestamp": 1696527824336,
      "trxId": "dfg",
      "username": "484805"
    },
    "-Ng-xpCU3n-jVDLVloo2": {
      "amount": "200",
      "chain": "USDT(BEP-20)",
      "id": "DQqP1eorEBf8n48PBWAQYxRfQoS2",
      "level": "1",
      "referredBy": "793175",
      "request": "Deposit",
      "requestId": "-Ng-xpCU3n-jVDLVloo2",
      "status": "Completed",
      "timestamp": 1696528290309,
      "trxId": "sdf",
      "username": "665416"
    },
    "-Ng-yReKE4m1P9tJvpCY": {
      "amount": "400",
      "chain": "USDT(BEP-20)",
      "id": "DQqP1eorEBf8n48PBWAQYxRfQoS2",
      "level": "2",
      "referredBy": "793175",
      "request": "Deposit",
      "requestId": "-Ng-yReKE4m1P9tJvpCY",
      "status": "Completed",
      "timestamp": 1696528451949,
      "trxId": "sdfsd",
      "username": "665416"
    },
    "-Ng-zhlu9jIakj22qzBs": {
      "amount": "600",
      "chain": "USDT(BEP-20)",
      "id": "DQqP1eorEBf8n48PBWAQYxRfQoS2",
      "level": "3",
      "referredBy": "793175",
      "request": "Deposit",
      "requestId": "-Ng-zhlu9jIakj22qzBs",
      "status": "Completed",
      "timestamp": 1696528784246,
      "trxId": "adsf",
      "username": "665416"
    },
    "-Ng-zhyljRmvVpBD31Uy": {
      "amount": "600",
      "chain": "USDT(BEP-20)",
      "id": "DQqP1eorEBf8n48PBWAQYxRfQoS2",
      "level": "3",
      "referredBy": "793175",
      "request": "Deposit",
      "requestId": "-Ng-zhyljRmvVpBD31Uy",
      "status": "Completed",
      "timestamp": 1696528785085,
      "trxId": "adsf",
      "username": "665416"
    },
    "-Ng0-CpwB4OAU6pb6pra": {
      "amount": "200",
      "chain": "USDT(BEP-20)",
      "id": "hAAFczQnMtOvyywM6g2T4eqEvDD3",
      "level": "1",
      "referredBy": "793175",
      "request": "Deposit",
      "requestId": "-Ng0-CpwB4OAU6pb6pra",
      "status": "Pending",
      "timestamp": 1696528915525,
      "trxId": "dfsfs",
      "username": "998324"
    },
    "-Ng0-DMrLk3jEykckrLE": {
      "amount": "200",
      "chain": "USDT(BEP-20)",
      "id": "hAAFczQnMtOvyywM6g2T4eqEvDD3",
      "level": "1",
      "referredBy": "793175",
      "request": "Deposit",
      "requestId": "-Ng0-DMrLk3jEykckrLE",
      "status": "Completed",
      "timestamp": 1696528917688,
      "trxId": "dfsfs",
      "username": "998324"
    },
    "-Ng0-_QaafkqWab7hwuN": {
      "amount": "400",
      "chain": "USDT(BEP-20)",
      "id": "qCz196NhHST7HNZ6wVgZa1Lqvfn1",
      "level": "2",
      "referredBy": "793175",
      "request": "Deposit",
      "requestId": "-Ng0-_QaafkqWab7hwuN",
      "status": "Completed",
      "timestamp": 1696529012123,
      "trxId": "sgfdgs",
      "username": "095846"
    },
    "-Ng0-_mIU0IL4DZdibqr": {
      "amount": "400",
      "chain": "USDT(BEP-20)",
      "id": "qCz196NhHST7HNZ6wVgZa1Lqvfn1",
      "level": "2",
      "referredBy": "793175",
      "request": "Deposit",
      "requestId": "-Ng0-_mIU0IL4DZdibqr",
      "status": "Completed",
      "timestamp": 1696529013569,
      "trxId": "sgfdgs",
      "username": "095846"
    },
    "-Ng0-wO3iMSszaD_fKtE": {
      "amount": "600",
      "chain": "USDT(BEP-20)",
      "id": "B34ZB29qiZQTPTmCgkqaofyGppn1",
      "level": "3",
      "referredBy": "793175",
      "request": "Deposit",
      "requestId": "-Ng0-wO3iMSszaD_fKtE",
      "status": "Completed",
      "timestamp": 1696529106211,
      "trxId": "hfj",
      "username": "719240"
    },
    "-Ng00HL78-5jSqqm2Ymm": {
      "amount": "1500",
      "chain": "USDT(BEP-20)",
      "id": "u8Mdv9xvD4bW8bEUfchLoN0ucn22",
      "level": "6",
      "referredBy": "793175",
      "request": "Deposit",
      "requestId": "-Ng00HL78-5jSqqm2Ymm",
      "status": "Completed",
      "timestamp": 1696529196085,
      "trxId": "fdg",
      "username": "484805"
    },
    "-Ng00HklAi0vHT4QKN2G": {
      "amount": "1500",
      "chain": "USDT(BEP-20)",
      "id": "u8Mdv9xvD4bW8bEUfchLoN0ucn22",
      "level": "6",
      "referredBy": "793175",
      "request": "Deposit",
      "requestId": "-Ng00HklAi0vHT4QKN2G",
      "status": "Completed",
      "timestamp": 1696529197784,
      "trxId": "fdg",
      "username": "484805"
    }
  },
  "supportLink": "https://www.youtube.com/watch?v=tw8iapinxou&ab_channel=almaferovi%c4%87-topic",
  "userAgreement": "My name is maviya",
  "users": {
    "793175": {
      "balance": 950,
      "country": "Belgium",
      "dateOfBirth": "11222022",
      "earned": 0,
      "email": "isafeer416@gmail.com",
      "firstRefferalPayment": true,
      "isAgent": true,
      "lastUpdate": "2023-09-30T14:23:13.389Z",
      "level": 3,
      "name": "Safeer Iqbal",
      "password": "safeer123",
      "plan": 600,
      "referrals": {
        "167988": {
          "approved": false,
          "profit": 0
        },
        "484805": {
          "approved": true,
          "profit": 0
        },
        "491457": {
          "approved": false,
          "profit": 0
        },
        "665416": {
          "approved": true,
          "profit": 0
        },
        "719240": {
          "approved": true,
          "profit": 0
        },
        "991612": {
          "approved": false,
          "profit": 0
        },
        "998324": {
          "approved": true,
          "profit": 0
        },
        "095846": {
          "approved": true,
          "profit": 0
        }
      },
      "referredBy": "767740",
      "refferalEarning": 850,
      "withdrawalAddress": "test wallet address",
      "withdrawalPIN": "3510"
    }
  }
}